pqc_binary_format/__init__.py
pqc_binary_format/pqc_binary_format.cpython-311-x86_64-linux-gnu.so
pqc_binary_format-1.0.14.dist-info/METADATA
pqc_binary_format-1.0.14.dist-info/WHEEL
pqc_binary_format-1.0.14.dist-info/licenses/LICENSE-APACHE
pqc_binary_format-1.0.14.dist-info/licenses/LICENSE-MIT
pqc_binary_format-1.0.14.dist-info/RECORD
