Metadata-Version: 2.4
Name: pqc_binary_format
Version: 1.0.14
Classifier: Development Status :: 5 - Production/Stable
Classifier: Intended Audience :: Developers
Classifier: License :: OSI Approved :: MIT License
Classifier: License :: OSI Approved :: Apache Software License
Classifier: Programming Language :: Python :: 3
Classifier: Programming Language :: Python :: 3.8
Classifier: Programming Language :: Python :: 3.9
Classifier: Programming Language :: Python :: 3.10
Classifier: Programming Language :: Python :: 3.11
Classifier: Programming Language :: Python :: 3.12
Classifier: Programming Language :: Rust
Classifier: Topic :: Security :: Cryptography
License-File: LICENSE-APACHE
License-File: LICENSE-MIT
Summary: Standardized binary format for post-quantum cryptography encrypted data interchange
Keywords: cryptography,post-quantum,pqc,encryption,binary-format
Home-Page: https://pqcrypta.com
Author-email: Allan <allan@pqcrypta.com>
License: MIT OR Apache-2.0
Requires-Python: >=3.8
Project-URL: Documentation, https://docs.rs/pqc-binary-format
Project-URL: Homepage, https://pqcrypta.com
Project-URL: Repository, https://github.com/PQCrypta/pqcrypta-community
